[
  {
    "id": 1,
    "thumb": "/images/skills/js.png",
    "title": "JavaScript",
    "experience": "6 Years"
  },
  {
    "id": 2,
    "thumb": "/images/skills/react.png",
    "title": "React",
    "experience": "5 Years"
  },
  {
    "id": 3,
    "thumb": "/images/skills/html.png",
    "title": "HTML",
    "experience": "6 Years"
  },
  {
    "id": 4,
    "thumb": "/images/skills/css.png",
    "title": "CSS",
    "experience": "6 Years"
  },
  {
    "id": 5,
    "thumb": "/images/skills/sass.png",
    "title": "SASS",
    "experience": "4 Years"
  },
  {
    "id": 6,
    "thumb": "/images/skills/redux.png",
    "title": "Redux",
    "experience": "2 Year"
  },
  {
    "id": 7,
    "thumb": "/images/skills/jest.png",
    "title": "Jest",
    "experience": "3 Years"
  },
  {
    "id": 8,
    "thumb": "/images/skills/node.png",
    "title": "Node",
    "experience": "2 Years"
  },
  {
    "id": 9,
    "thumb": "/images/skills/git.png",
    "title": "Git",
    "experience": "5 Years"
  },
  {
    "id": 10,
    "thumb": "/images/skills/Vue.png",
    "title": "Vue",
    "experience": "1 Year"
  },
  {
    "id": 11,
    "thumb": "/images/skills/wordpress.png",
    "title": "Wordpress",
    "experience": "4 Years"
  },
  {
    "id": 12,
    "thumb": "/images/skills/typescript.png",
    "title": "TypeScript",
    "experience": "2 Year"
  },
  {
    "id": 13,
    "thumb": "/images/skills/web-components.png",
    "title": "Web Components",
    "experience": "1 Year"
  },
  {
    "id": 14,
    "thumb": "/images/skills/figma.png",
    "title": "Figma",
    "experience": "5 Years"
  },
  {
    "id": 15,
    "thumb": "/images/skills/xd.png",
    "title": "Adobe XD",
    "experience": "5 Years"
  },
  {
    "id": 16,
    "thumb": "/images/skills/docker.png",
    "title": "Docker",
    "experience": "1 Year"
  }
]
